tweetvac.py
tweetvac-1.0.1.dist-info/LICENSE
tweetvac-1.0.1.dist-info/METADATA
tweetvac-1.0.1.dist-info/WHEEL
tweetvac-1.0.1.dist-info/top_level.txt
tweetvac-1.0.1.dist-info/RECORD
