Metadata-Version: 2.1
Name: tweetvac
Version: 1.0.1
Summary: Package that makes sucking down tweets from Twitter easy.
Home-page: https://github.com/cash/tweetvac
Author: Cash Costello
Author-email: cash.costello@gmail.com
License: MIT
Keywords: twitter tweet tweetvac cursor client
Platform: UNKNOWN
Classifier: Development Status :: 5 - Production/Stable
Classifier: Environment :: Console
Classifier: Intended Audience :: Developers
Classifier: Intended Audience :: Science/Research
Classifier: License :: OSI Approved :: MIT License
Classifier: Natural Language :: English
Classifier: Operating System :: OS Independent
Classifier: Programming Language :: Python
Classifier: Programming Language :: Python :: 3
Classifier: Topic :: Internet :: WWW/HTTP
Classifier: Topic :: Software Development :: Libraries :: Python Modules
Requires-Dist: twython (>=3.0.0)
